thinkpdf/__init__.py
thinkpdf/__main__.py
thinkpdf/app_gui.py
thinkpdf/cli.py
thinkpdf/engine.py
thinkpdf/logger.py
thinkpdf/mcp_server.py
thinkpdf/cache/__init__.py
thinkpdf/cache/cache_manager.py
thinkpdf/core/__init__.py
thinkpdf/core/converter.py
thinkpdf/core/equations.py
thinkpdf/core/extract.py
thinkpdf/core/extractor.py
thinkpdf/core/models.py
thinkpdf/core/pipeline.py
thinkpdf/core/render.py
thinkpdf/core/tables.py
thinkpdf/core/transform.py
thinkpdf/core/utils.py
thinkpdf/utils/__init__.py
thinkpdf-1.0.5.dist-info/licenses/LICENSE
thinkpdf-1.0.5.dist-info/METADATA
thinkpdf-1.0.5.dist-info/WHEEL
thinkpdf-1.0.5.dist-info/entry_points.txt
thinkpdf-1.0.5.dist-info/top_level.txt
thinkpdf-1.0.5.dist-info/RECORD
